<annotation>
	<folder>uav_000041</folder>
	<filename>000518.jpg</filename>
	<path>E:\dataset_label\AerialDataset_0.1\JPEGImages\uav_000041\000518.jpg</path>
	<source>
		<database>Unknown</database>
	</source>
	<size>
		<width>960</width>
		<height>540</height>
		<depth>3</depth>
	</size>
	<segmented>0</segmented>
	<object>
		<name>car</name>
		<pose>Unspecified</pose>
		<truncated>1</truncated>
		<difficult>0</difficult>
		<bndbox>
			<xmin>846</xmin>
			<ymin>192</ymin>
			<xmax>960</xmax>
			<ymax>375</ymax>
		</bndbox>
	</object>
	<object>
		<name>person</name>
		<pose>Unspecified</pose>
		<truncated>0</truncated>
		<difficult>0</difficult>
		<bndbox>
			<xmin>525</xmin>
			<ymin>210</ymin>
			<xmax>560</xmax>
			<ymax>260</ymax>
		</bndbox>
	</object>
</annotation>
