<annotation>
	<folder>uav_000037</folder>
	<filename>000008.jpg</filename>
	<path>E:\dataset_label\AerialDataset_0.1\JPEGImages\uav_000037\000008.jpg</path>
	<source>
		<database>Unknown</database>
	</source>
	<size>
		<width>1920</width>
		<height>1080</height>
		<depth>3</depth>
	</size>
	<segmented>0</segmented>
	<object>
		<name>truck</name>
		<pose>Unspecified</pose>
		<truncated>0</truncated>
		<difficult>0</difficult>
		<bndbox>
			<xmin>1370</xmin>
			<ymin>187</ymin>
			<xmax>1624</xmax>
			<ymax>428</ymax>
		</bndbox>
	</object>
	<object>
		<name>person</name>
		<pose>Unspecified</pose>
		<truncated>0</truncated>
		<difficult>0</difficult>
		<bndbox>
			<xmin>906</xmin>
			<ymin>394</ymin>
			<xmax>1002</xmax>
			<ymax>635</ymax>
		</bndbox>
	</object>
	<object>
		<name>bicycle</name>
		<pose>Unspecified</pose>
		<truncated>0</truncated>
		<difficult>0</difficult>
		<bndbox>
			<xmin>720</xmin>
			<ymin>204</ymin>
			<xmax>828</xmax>
			<ymax>382</ymax>
		</bndbox>
	</object>
	<object>
		<name>car</name>
		<pose>Unspecified</pose>
		<truncated>0</truncated>
		<difficult>0</difficult>
		<bndbox>
			<xmin>117</xmin>
			<ymin>476</ymin>
			<xmax>564</xmax>
			<ymax>837</ymax>
		</bndbox>
	</object>
	<object>
		<name>car</name>
		<pose>Unspecified</pose>
		<truncated>0</truncated>
		<difficult>0</difficult>
		<bndbox>
			<xmin>91</xmin>
			<ymin>298</ymin>
			<xmax>213</xmax>
			<ymax>460</ymax>
		</bndbox>
	</object>
	<object>
		<name>car</name>
		<pose>Unspecified</pose>
		<truncated>0</truncated>
		<difficult>0</difficult>
		<bndbox>
			<xmin>239</xmin>
			<ymin>239</ymin>
			<xmax>375</xmax>
			<ymax>376</ymax>
		</bndbox>
	</object>
</annotation>
