<annotation>
	<folder>uav_000043</folder>
	<filename>000050.jpg</filename>
	<path>E:\dataset_label\AerialDataset_0.1\JPEGImages\uav_000043\000050.jpg</path>
	<source>
		<database>Unknown</database>
	</source>
	<size>
		<width>1200</width>
		<height>674</height>
		<depth>3</depth>
	</size>
	<segmented>0</segmented>
	<object>
		<name>person</name>
		<pose>Unspecified</pose>
		<truncated>0</truncated>
		<difficult>0</difficult>
		<bndbox>
			<xmin>396</xmin>
			<ymin>83</ymin>
			<xmax>474</xmax>
			<ymax>188</ymax>
		</bndbox>
	</object>
	<object>
		<name>person</name>
		<pose>Unspecified</pose>
		<truncated>0</truncated>
		<difficult>0</difficult>
		<bndbox>
			<xmin>516</xmin>
			<ymin>37</ymin>
			<xmax>582</xmax>
			<ymax>125</ymax>
		</bndbox>
	</object>
	<object>
		<name>person</name>
		<pose>Unspecified</pose>
		<truncated>0</truncated>
		<difficult>0</difficult>
		<bndbox>
			<xmin>645</xmin>
			<ymin>52</ymin>
			<xmax>705</xmax>
			<ymax>145</ymax>
		</bndbox>
	</object>
	<object>
		<name>person</name>
		<pose>Unspecified</pose>
		<truncated>0</truncated>
		<difficult>0</difficult>
		<bndbox>
			<xmin>747</xmin>
			<ymin>106</ymin>
			<xmax>793</xmax>
			<ymax>220</ymax>
		</bndbox>
	</object>
	<object>
		<name>person</name>
		<pose>Unspecified</pose>
		<truncated>0</truncated>
		<difficult>0</difficult>
		<bndbox>
			<xmin>803</xmin>
			<ymin>200</ymin>
			<xmax>861</xmax>
			<ymax>291</ymax>
		</bndbox>
	</object>
	<object>
		<name>person</name>
		<pose>Unspecified</pose>
		<truncated>0</truncated>
		<difficult>0</difficult>
		<bndbox>
			<xmin>634</xmin>
			<ymin>204</ymin>
			<xmax>687</xmax>
			<ymax>286</ymax>
		</bndbox>
	</object>
	<object>
		<name>person</name>
		<pose>Unspecified</pose>
		<truncated>0</truncated>
		<difficult>0</difficult>
		<bndbox>
			<xmin>616</xmin>
			<ymin>286</ymin>
			<xmax>711</xmax>
			<ymax>356</ymax>
		</bndbox>
	</object>
	<object>
		<name>person</name>
		<pose>Unspecified</pose>
		<truncated>0</truncated>
		<difficult>0</difficult>
		<bndbox>
			<xmin>556</xmin>
			<ymin>323</ymin>
			<xmax>641</xmax>
			<ymax>438</ymax>
		</bndbox>
	</object>
	<object>
		<name>person</name>
		<pose>Unspecified</pose>
		<truncated>0</truncated>
		<difficult>0</difficult>
		<bndbox>
			<xmin>424</xmin>
			<ymin>452</ymin>
			<xmax>526</xmax>
			<ymax>513</ymax>
		</bndbox>
	</object>
</annotation>
