<annotation>
	<folder>uav_000001</folder>
	<filename>000112.jpg</filename>
	<path>E:\dataset_label\AerialDataset_0.1\JPEGImages\uav_000001\000112.jpg</path>
	<source>
		<database>Unknown</database>
	</source>
	<size>
		<width>960</width>
		<height>540</height>
		<depth>3</depth>
	</size>
	<segmented>0</segmented>
	<object>
		<name>person</name>
		<pose>Unspecified</pose>
		<truncated>0</truncated>
		<difficult>0</difficult>
		<bndbox>
			<xmin>727</xmin>
			<ymin>399</ymin>
			<xmax>758</xmax>
			<ymax>454</ymax>
		</bndbox>
	</object>
	<object>
		<name>person</name>
		<pose>Unspecified</pose>
		<truncated>0</truncated>
		<difficult>0</difficult>
		<bndbox>
			<xmin>784</xmin>
			<ymin>412</ymin>
			<xmax>819</xmax>
			<ymax>464</ymax>
		</bndbox>
	</object>
	<object>
		<name>car</name>
		<pose>Unspecified</pose>
		<truncated>0</truncated>
		<difficult>0</difficult>
		<bndbox>
			<xmin>521</xmin>
			<ymin>255</ymin>
			<xmax>595</xmax>
			<ymax>291</ymax>
		</bndbox>
	</object>
	<object>
		<name>car</name>
		<pose>Unspecified</pose>
		<truncated>0</truncated>
		<difficult>0</difficult>
		<bndbox>
			<xmin>740</xmin>
			<ymin>398</ymin>
			<xmax>818</xmax>
			<ymax>461</ymax>
		</bndbox>
	</object>
</annotation>
