<annotation>
	<folder>uav_000042</folder>
	<filename>000045.jpg</filename>
	<path>E:\dataset_label\AerialDataset_0.1\JPEGImages\uav_000042\000045.jpg</path>
	<source>
		<database>Unknown</database>
	</source>
	<size>
		<width>2000</width>
		<height>1500</height>
		<depth>3</depth>
	</size>
	<segmented>0</segmented>
	<object>
		<name>person</name>
		<pose>Unspecified</pose>
		<truncated>0</truncated>
		<difficult>0</difficult>
		<bndbox>
			<xmin>869</xmin>
			<ymin>348</ymin>
			<xmax>968</xmax>
			<ymax>619</ymax>
		</bndbox>
	</object>
	<object>
		<name>person</name>
		<pose>Unspecified</pose>
		<truncated>0</truncated>
		<difficult>0</difficult>
		<bndbox>
			<xmin>1344</xmin>
			<ymin>480</ymin>
			<xmax>1453</xmax>
			<ymax>757</ymax>
		</bndbox>
	</object>
	<object>
		<name>person</name>
		<pose>Unspecified</pose>
		<truncated>0</truncated>
		<difficult>0</difficult>
		<bndbox>
			<xmin>1555</xmin>
			<ymin>460</ymin>
			<xmax>1650</xmax>
			<ymax>764</ymax>
		</bndbox>
	</object>
	<object>
		<name>person</name>
		<pose>Unspecified</pose>
		<truncated>0</truncated>
		<difficult>0</difficult>
		<bndbox>
			<xmin>1698</xmin>
			<ymin>527</ymin>
			<xmax>1806</xmax>
			<ymax>860</ymax>
		</bndbox>
	</object>
	<object>
		<name>person</name>
		<pose>Unspecified</pose>
		<truncated>0</truncated>
		<difficult>0</difficult>
		<bndbox>
			<xmin>477</xmin>
			<ymin>887</ymin>
			<xmax>617</xmax>
			<ymax>1224</ymax>
		</bndbox>
	</object>
	<object>
		<name>person</name>
		<pose>Unspecified</pose>
		<truncated>0</truncated>
		<difficult>0</difficult>
		<bndbox>
			<xmin>474</xmin>
			<ymin>648</ymin>
			<xmax>580</xmax>
			<ymax>945</ymax>
		</bndbox>
	</object>
	<object>
		<name>car</name>
		<pose>Unspecified</pose>
		<truncated>0</truncated>
		<difficult>0</difficult>
		<bndbox>
			<xmin>74</xmin>
			<ymin>37</ymin>
			<xmax>526</xmax>
			<ymax>226</ymax>
		</bndbox>
	</object>
	<object>
		<name>car</name>
		<pose>Unspecified</pose>
		<truncated>0</truncated>
		<difficult>0</difficult>
		<bndbox>
			<xmin>1325</xmin>
			<ymin>73</ymin>
			<xmax>1785</xmax>
			<ymax>316</ymax>
		</bndbox>
	</object>
	<object>
		<name>car</name>
		<pose>Unspecified</pose>
		<truncated>0</truncated>
		<difficult>0</difficult>
		<bndbox>
			<xmin>1152</xmin>
			<ymin>837</ymin>
			<xmax>1956</xmax>
			<ymax>1221</ymax>
		</bndbox>
	</object>
	<object>
		<name>car</name>
		<pose>Unspecified</pose>
		<truncated>0</truncated>
		<difficult>0</difficult>
		<bndbox>
			<xmin>1014</xmin>
			<ymin>1029</ymin>
			<xmax>1583</xmax>
			<ymax>1376</ymax>
		</bndbox>
	</object>
	<object>
		<name>car</name>
		<pose>Unspecified</pose>
		<truncated>0</truncated>
		<difficult>0</difficult>
		<bndbox>
			<xmin>626</xmin>
			<ymin>1124</ymin>
			<xmax>1212</xmax>
			<ymax>1460</ymax>
		</bndbox>
	</object>
</annotation>
