<annotation>
	<folder>uav_000003</folder>
	<filename>000451.jpg</filename>
	<path>E:\dataset_label\AerialDataset_0.1\JPEGImages\uav_000003\000451.jpg</path>
	<source>
		<database>Unknown</database>
	</source>
	<size>
		<width>960</width>
		<height>540</height>
		<depth>3</depth>
	</size>
	<segmented>0</segmented>
	<object>
		<name>car</name>
		<pose>Unspecified</pose>
		<truncated>0</truncated>
		<difficult>0</difficult>
		<bndbox>
			<xmin>443</xmin>
			<ymin>42</ymin>
			<xmax>463</xmax>
			<ymax>54</ymax>
		</bndbox>
	</object>
	<object>
		<name>car</name>
		<pose>Unspecified</pose>
		<truncated>0</truncated>
		<difficult>0</difficult>
		<bndbox>
			<xmin>502</xmin>
			<ymin>41</ymin>
			<xmax>521</xmax>
			<ymax>58</ymax>
		</bndbox>
	</object>
	<object>
		<name>car</name>
		<pose>Unspecified</pose>
		<truncated>0</truncated>
		<difficult>0</difficult>
		<bndbox>
			<xmin>789</xmin>
			<ymin>249</ymin>
			<xmax>872</xmax>
			<ymax>278</ymax>
		</bndbox>
	</object>
	<object>
		<name>person</name>
		<pose>Unspecified</pose>
		<truncated>0</truncated>
		<difficult>0</difficult>
		<bndbox>
			<xmin>603</xmin>
			<ymin>424</ymin>
			<xmax>621</xmax>
			<ymax>470</ymax>
		</bndbox>
	</object>
	<object>
		<name>person</name>
		<pose>Unspecified</pose>
		<truncated>0</truncated>
		<difficult>0</difficult>
		<bndbox>
			<xmin>627</xmin>
			<ymin>484</ymin>
			<xmax>639</xmax>
			<ymax>523</ymax>
		</bndbox>
	</object>
</annotation>
